MANIFEST.in
README.rst
setup.cfg
setup.py
positronium/Bohr.py
positronium/Ferrell.py
positronium/Ps.py
positronium/__init__.py
positronium/antimattergravity.py
positronium/constants.py
positronium.egg-info/PKG-INFO
positronium.egg-info/SOURCES.txt
positronium.egg-info/dependency_links.txt
positronium.egg-info/not-zip-safe
positronium.egg-info/requires.txt
positronium.egg-info/top_level.txt